Metadata-Version: 1.0
Name: jag-probability-distributions
Version: 0.2
Summary: Gaussian and Binomial distributions
Home-page: UNKNOWN
Author: Jeroen Goddijn
Author-email: jeroen.goddijn@gmail.com
License: UNKNOWN
Platform: UNKNOWN
